MANIFEST.in
README.rst
setup.cfg
setup.py
contactform/__init__.py
contactform/helpers.py
contactform/controllers/__init__.py
contactform/controllers/root.py
contactform/i18n/contactform.pot
contactform/i18n/it/LC_MESSAGES/contactform.mo
contactform/i18n/it/LC_MESSAGES/contactform.po
contactform/lib/__init__.py
contactform/public/__init__.py
contactform/templates/__init__.py
contactform/templates/index.html
contactform/templates/index.xhtml
tgapp_contactform.egg-info/PKG-INFO
tgapp_contactform.egg-info/SOURCES.txt
tgapp_contactform.egg-info/dependency_links.txt
tgapp_contactform.egg-info/entry_points.txt
tgapp_contactform.egg-info/not-zip-safe
tgapp_contactform.egg-info/requires.txt
tgapp_contactform.egg-info/top_level.txt