Metadata-Version: 1.0
Name: tgapp-contactform
Version: 0.0.3
Summary: tgapp-contactform is a Pluggable application for TurboGears2 that shows a simple contact form.
Home-page: https://bitbucket.org/axant/tgapp-contactform
Author: AXANT
Author-email: tech@axant.it
License: UNKNOWN
Keywords: turbogears2.application
Platform: UNKNOWN
